recommendation/__init__.py
recommendation/api/__init__.py
recommendation/api/api.py
recommendation/api/helper.py
recommendation/api/external_data/__init__.py
recommendation/api/external_data/fetcher.py
recommendation/api/external_data/wikidata.py
recommendation/api/types/__init__.py
recommendation/api/types/related_articles/__init__.py
recommendation/api/types/related_articles/candidate_finder.py
recommendation/api/types/related_articles/related_articles.py
recommendation/api/types/translation/__init__.py
recommendation/api/types/translation/candidate_finders.py
recommendation/api/types/translation/filters.py
recommendation/api/types/translation/pageviews.py
recommendation/api/types/translation/recommendation.py
recommendation/api/types/translation/translation.py
recommendation/data/labs_setup.sh
recommendation/data/recommendation.ini
recommendation/data/recommendation.nginx
recommendation/data/recommendation.service
recommendation/data/recommendation.wsgi
recommendation/data/release.sh
recommendation/data/uwsgi.ini
recommendation/utils/__init__.py
recommendation/utils/configuration.py
recommendation/utils/event_logger.py
recommendation/utils/language_pairs.py
recommendation/utils/logger.py
recommendation/web/__init__.py
recommendation/web/gapfinder.py
recommendation/web/static/bower.json
recommendation/web/static/cookies.js
recommendation/web/static/event_logger.js
recommendation/web/static/gf-articles.tag
recommendation/web/static/gf-create.tag
recommendation/web/static/gf-disclaimer.tag
recommendation/web/static/gf-input.tag
recommendation/web/static/gf-preview.tag
recommendation/web/static/gf-title.tag
recommendation/web/static/style.css
recommendation/web/static/i18n/ar.json
recommendation/web/static/i18n/ast.json
recommendation/web/static/i18n/azb.json
recommendation/web/static/i18n/be-tarask.json
recommendation/web/static/i18n/bn.json
recommendation/web/static/i18n/br.json
recommendation/web/static/i18n/bs.json
recommendation-0.3.1.dist-info/DESCRIPTION.rst
recommendation-0.3.1.dist-info/METADATA
recommendation-0.3.1.dist-info/RECORD
recommendation-0.3.1.dist-info/WHEEL
recommendation-0.3.1.dist-info/metadata.json
recommendation-0.3.1.dist-info/top_level.txt
