Metadata-Version: 1.0
Name: recommendation
Version: 0.3.1
Summary: Provide recommendations in Wikimedia projects
Home-page: https://github.com/wikimedia/research-recommendation-api
Author: Wikimedia Research
Author-email: nschaaf@wikimedia.org
License: Apache Software License
Platform: UNKNOWN
